geoworker.py
geoworker-0.0.6.dist-info/LICENSE
geoworker-0.0.6.dist-info/METADATA
geoworker-0.0.6.dist-info/WHEEL
geoworker-0.0.6.dist-info/top_level.txt
geoworker-0.0.6.dist-info/RECORD
